cerberius_python_client/__init__.py
cerberius_python_client/client.py
cerberius_python_client/models/__init__.py
cerberius_python_client/models/data_models.py
cerberius_python_client-0.1.1.dist-info/LICENSE
cerberius_python_client-0.1.1.dist-info/METADATA
cerberius_python_client-0.1.1.dist-info/WHEEL
cerberius_python_client-0.1.1.dist-info/RECORD
