Metadata-Version: 2.3
Name: cerberius-python-client
Version: 0.1.1
Summary: A Python client for the Cerberius API.
License: MIT
Keywords: cerberius,api,client,security,ip lookup,email validation,prompt classification
Author: Stas Solodkin
Author-email: stas@cerberius.com
Requires-Python: >=3.7
Classifier: Development Status :: 3 - Alpha
Classifier: Intended Audience :: Developers
Classifier: License :: OSI Approved :: MIT License
Classifier: Operating System :: OS Independent
Classifier: Programming Language :: Python :: 3
Classifier: Programming Language :: Python :: 3.7
Classifier: Programming Language :: Python :: 3.8
Classifier: Programming Language :: Python :: 3.9
Classifier: Programming Language :: Python :: 3.10
Classifier: Programming Language :: Python :: 3.11
Classifier: Programming Language :: Python :: 3.12
Classifier: Programming Language :: Python :: 3.13
Requires-Dist: requests (>=2.25.1,<3.0.0)
Project-URL: Homepage, https://github.com/cerberius-lab/cerberius-python-client
Project-URL: Repository, https://github.com/cerberius-lab/cerberius-python-client
